diffpy/__init__.py
diffpy/srreal/__init__.py
diffpy/srreal/_cleanup.py
diffpy/srreal/_docstrings.py
diffpy/srreal/_final_imports.py
diffpy/srreal/atomradiitable.py
diffpy/srreal/attributes.py
diffpy/srreal/bondcalculator.py
diffpy/srreal/bvparameterstable.py
diffpy/srreal/bvscalculator.py
diffpy/srreal/eventticker.py
diffpy/srreal/overlapcalculator.py
diffpy/srreal/pairquantity.py
diffpy/srreal/parallel.py
diffpy/srreal/pdfbaseline.py
diffpy/srreal/pdfcalculator.py
diffpy/srreal/pdfenvelope.py
diffpy/srreal/peakprofile.py
diffpy/srreal/peakwidthmodel.py
diffpy/srreal/scatteringfactortable.py
diffpy/srreal/sfaverage.py
diffpy/srreal/srreal_ext.cpython-312-darwin.so
diffpy/srreal/structureadapter.py
diffpy/srreal/structureconverters.py
diffpy/srreal/version.py
diffpy/srreal/wraputils.py
diffpy/srreal/devutils/tunePeakPrecision.py
diffpy_srreal-1.4.0.dist-info/licenses/AUTHORS.rst
diffpy_srreal-1.4.0.dist-info/licenses/LICENSE.rst
diffpy_srreal-1.4.0.dist-info/licenses/LICENSE_DANSE.rst
diffpy_srreal-1.4.0.dist-info/METADATA
diffpy_srreal-1.4.0.dist-info/WHEEL
diffpy_srreal-1.4.0.dist-info/top_level.txt
diffpy_srreal-1.4.0.dist-info/RECORD
